bfutils/__init__.py
bfutils/constants.py
bfutils/file.py
bfutils/data/Orbit_Path_Time.json
bfutils/data/Orbit_Path_Time.txt
bfutils/data/config.yml
bfutils-0.1.0.dist-info/METADATA
bfutils-0.1.0.dist-info/RECORD
bfutils-0.1.0.dist-info/WHEEL
bfutils-0.1.0.dist-info/top_level.txt
