Metadata-Version: 2.1
Name: bfutils
Version: 0.1.0
Summary: Basic Fusion utilities
Home-page: https://github.com/TerraFusion/bfutils
Author: Landon T. Clipp
Author-email: clipp2@illinois.edu
License: UNKNOWN
Keywords: bfutils,bf,utilities,nasa,eos,earth
Platform: UNKNOWN
Requires-Dist: pyyaml
